zkyhaxpy/__init__.py
zkyhaxpy/aws_tools.py
zkyhaxpy/binary_tools.py
zkyhaxpy/colab_tools.py
zkyhaxpy/console_tools.py
zkyhaxpy/cryptography_tools.py
zkyhaxpy/data_package_tools.py
zkyhaxpy/dict_tools.py
zkyhaxpy/dttm_tools.py
zkyhaxpy/ftp_tools.py
zkyhaxpy/gcp_tools.py
zkyhaxpy/gis_tools.py
zkyhaxpy/gis_tools_no_gdal.py
zkyhaxpy/hash_tools.py
zkyhaxpy/http_tools.py
zkyhaxpy/img_tools.py
zkyhaxpy/io_tools.py
zkyhaxpy/json_tools.py
zkyhaxpy/jupyter_tools.py
zkyhaxpy/log_tools.py
zkyhaxpy/ml_tools.py
zkyhaxpy/mpl_tools.py
zkyhaxpy/multitask_tools.py
zkyhaxpy/np_tools.py
zkyhaxpy/pd_tools.py
zkyhaxpy/skopt_tools.py
zkyhaxpy/snippet_tools.py
zkyhaxpy/str_tools.py
zkyhaxpy/timer_tools.py
zkyhaxpy/util_tools.py
zkyhaxpy/viz_tools.py
zkyhaxpy/data_package/__init__.py
zkyhaxpy/data_package/ms-toolsai.datawrangler-1.24.0.vsix
zkyhaxpy/data_package/tambon_urban.csv
zkyhaxpy/misc/__init__.py
zkyhaxpy/misc/data_for_fraud_project.py
zkyhaxpy/misc/population_stats.py
zkyhaxpy/misc/postcode.py
zkyhaxpy/misc/shapes.py
zkyhaxpy-0.3.1.4.5.dist-info/licenses/LICENSE
zkyhaxpy-0.3.1.4.5.dist-info/METADATA
zkyhaxpy-0.3.1.4.5.dist-info/WHEEL
zkyhaxpy-0.3.1.4.5.dist-info/top_level.txt
zkyhaxpy-0.3.1.4.5.dist-info/RECORD
