Metadata-Version: 2.4
Name: zkyhaxpy
Version: 0.3.1.4.5
Summary: A swiss-knife Data Science package for python
Author-email: Surasak Choedpasuporn <surasak.cho@gmail.com>
Project-URL: Homepage, https://github.com/surasakcho/zkyhaxpy
Classifier: Programming Language :: Python :: 3
Classifier: License :: OSI Approved :: MIT License
Classifier: Operating System :: OS Independent
Requires-Python: >=3.6
License-File: LICENSE
Requires-Dist: pandas
Requires-Dist: numpy
Dynamic: license-file
